{"name":"BarItemType","summary":"<p>Object describing a button bar or tabbed bar item.</p>\n","extends":"Object","platforms":[{"since":"0.8","name":"android"},{"since":"0.8","name":"iphone"},{"since":"0.8","name":"ipad"}],"type":"pseudo","properties":[{"name":"accessibilityLabel","summary":"<p>A succint label associated with the bar item for the device's accessibility service.</p>\n","description":"<p>See <a href=\"/titanium-docs/api/titanium/ui/view.html#accessibilitylabel\">accessibilityLabel</a> description.</p>\n","platforms":[{"since":"3.0.0","name":"iphone"},{"since":"3.0.0","name":"ipad"}],"type":"String"},{"name":"enabled","summary":"<p>Whether the button is enabled initially.</p>\n","platforms":[{"since":"0.8","name":"android"},{"since":"0.8","name":"iphone"},{"since":"0.8","name":"ipad"}],"type":"Boolean","default":true},{"name":"image","summary":"<p>Button icon. If specified, takes precedence over <code>title</code>.</p>\n","platforms":[{"since":"0.8","name":"android"},{"since":"0.8","name":"iphone"},{"since":"0.8","name":"ipad"}],"type":["String","Titanium.Blob","Titanium.Filesystem.File"]},{"name":"title","summary":"<p>Button title, used if no <code>image</code> is specified.</p>\n","platforms":[{"since":"0.8","name":"android"},{"since":"0.8","name":"iphone"},{"since":"0.8","name":"ipad"}],"type":"String"},{"name":"width","summary":"<p>Width for this button.</p>\n","platforms":[{"since":"0.8","name":"android"},{"since":"0.8","name":"iphone"},{"since":"0.8","name":"ipad"}],"type":"Number"}],"methods":[],"events":[],"constants":[]}
