{"name":"Titanium.XML.Notation","summary":"<p>Represents a notation declared in the DTD.  Implements the <a href=\"https://www.w3.org/TR/DOM-Level-2-Core/core.html#ID-5431D1B9\">DOM Level 2 API</a> on Android and iOS.</p>\n","extends":"Titanium.Proxy","platforms":[{"since":"0.9","name":"android"},{"since":"0.9","name":"iphone"},{"since":"0.9","name":"ipad"},{"since":"9.2.0","name":"macos"},{"since":"4.1.0","name":"windowsphone"}],"type":"object","editUrl":"https://github.com/appcelerator/titanium_mobile/edit/master/apidoc/Titanium/XML/Notation.yml","methods":[],"properties":[{"name":"publicId","summary":"<p>The public identifier of this notation. If the public identifier was not specified, this is <code>null</code>.</p>\n","platforms":[{"since":"0.9","name":"android"},{"since":"0.9","name":"iphone"},{"since":"0.9","name":"ipad"},{"since":"9.2.0","name":"macos"},{"since":"4.1.0","name":"windowsphone"}],"type":"String","permission":"read-only"},{"name":"systemId","summary":"<p>The system identifier of this notation. If the system identifier was not specified, this is <code>null</code>.</p>\n","platforms":[{"since":"0.9","name":"android"},{"since":"0.9","name":"iphone"},{"since":"0.9","name":"ipad"},{"since":"9.2.0","name":"macos"},{"since":"4.1.0","name":"windowsphone"}],"type":"String","permission":"read-only"}],"subtype":"proxy","events":[],"constants":[]}
