{"name":"Titanium.Geolocation.Android.LocationProvider","summary":"<p>Represents a source of location information, such as GPS.</p>\n","extends":"Titanium.Proxy","platforms":[{"pretty_name":"Android","since":"2.0.0","name":"android"}],"type":"object","methods":[],"properties":[{"name":"minUpdateDistance","summary":"<p>Don't send a location update unless the location has changed at least <code>minUpdateDistance</code>\nmeters since the previous update.</p>\n","filename":"Titanium.Geolocation.Android.LocationProvider.minUpdateDistance-property","platforms":[{"pretty_name":"Android","since":"2.0.0","name":"android"}],"type":"Number"},{"name":"minUpdateTime","summary":"<p>Limits the frequency of location updates to no more than one per <code>minUpdateTime</code> seconds.</p>\n","filename":"Titanium.Geolocation.Android.LocationProvider.minUpdateTime-property","platforms":[{"pretty_name":"Android","since":"2.0.0","name":"android"}],"type":"Number"},{"name":"name","summary":"<p>Type of location provider: <a href=\"/titanium-docs/api/titanium/geolocation/android.html#provider_gps\">PROVIDER_GPS</a>,\n<a href=\"/titanium-docs/api/titanium/geolocation/android.html#provider_network\">PROVIDER_NETWORK</a>, or\n<a href=\"/titanium-docs/api/titanium/geolocation/android.html#provider_passive\">PROVIDER_PASSIVE</a>.</p>\n","filename":"Titanium.Geolocation.Android.LocationProvider.name-property","platforms":[{"pretty_name":"Android","since":"2.0.0","name":"android"}],"type":"String"}],"subtype":"proxy","events":[],"constants":[]}